{
  "index_settings": {
    "docstore_compression": "lz4",
    "docstore_blocksize": 16384
  },
  "segments": [
    {
      "segment_id": "ab664f77-23e5-45d2-bf5d-4723dcf98f89",
      "max_doc": 102,
      "deletes": null
    },
    {
      "segment_id": "49168753-3234-445e-96fa-50a2bd31ac0e",
      "max_doc": 102,
      "deletes": null
    },
    {
      "segment_id": "68380784-93e4-4736-8e01-a5967fc7b3ee",
      "max_doc": 89,
      "deletes": null
    }
  ],
  "schema": [
    {
      "name": "content",
      "type": "text",
      "options": {
        "indexing": {
          "record": "position",
          "fieldnorms": true,
          "tokenizer": "default"
        },
        "stored": true,
        "fast": false
      }
    },
    {
      "name": "path",
      "type": "text",
      "options": {
        "indexing": {
          "record": "position",
          "fieldnorms": true,
          "tokenizer": "default"
        },
        "stored": true,
        "fast": false
      }
    },
    {
      "name": "package",
      "type": "text",
      "options": {
        "indexing": {
          "record": "position",
          "fieldnorms": true,
          "tokenizer": "default"
        },
        "stored": true,
        "fast": false
      }
    },
    {
      "name": "title",
      "type": "text",
      "options": {
        "indexing": {
          "record": "position",
          "fieldnorms": true,
          "tokenizer": "default"
        },
        "stored": true,
        "fast": false
      }
    },
    {
      "name": "source_repo",
      "type": "text",
      "options": {
        "indexing": {
          "record": "position",
          "fieldnorms": true,
          "tokenizer": "default"
        },
        "stored": true,
        "fast": false
      }
    },
    {
      "name": "docs_path",
      "type": "text",
      "options": {
        "indexing": {
          "record": "position",
          "fieldnorms": true,
          "tokenizer": "default"
        },
        "stored": true,
        "fast": false
      }
    }
  ],
  "opstamp": 296
}
